<?xml version="1.0" encoding="UTF-8"?>
<portlet-app xmlns="http://java.sun.com/xml/ns/portlet/portlet-app_2_0.xsd"
             version="2.0"
             xmlns:xsi="http://www.w3.org/2001/XMLSchema-instance"
             xsi:schemaLocation="http://java.sun.com/xml/ns/portlet/portlet-app_2_0.xsd
   http://java.sun.com/xml/ns/portlet/portlet-app_2_0.xsd">
  <portlet>
    <description xml:lang="EN">this application allows user to remove his account</description>
    <portlet-name>JuZRemoveMyAccountFrontendPortlet</portlet-name>
    <display-name xml:lang="EN">Juzu Remove My Account Frontend Portlet</display-name>
    <portlet-class>org.juzu.removemyaccount.portlet.frontend.FrontendPortlet</portlet-class>
    <supports>
      <mime-type>text/html</mime-type>
    </supports>
    <portlet-info>
      <title>Juz Remove My Account Application</title>
      <short-title>Juz Remove My Account Portlet</short-title>
      <keywords>remove-my-account-webapp</keywords>
    </portlet-info>
  </portlet>

  <portlet>
    <description xml:lang="EN">this application allows to add remove-account button in profile page</description>
    <portlet-name>JuzRemoveAccountProfileApplication</portlet-name>
    <display-name xml:lang="EN">Juzu Remove My Account Profile Portlet</display-name>
    <portlet-class>org.juzu.removemyaccount.portlet.profile.ProfilePorlet</portlet-class>
    <supports>
      <mime-type>text/html</mime-type>
    </supports>
    <portlet-info>
      <title>Remove My Account Profile Application</title>
      <short-title>Remove My Account Profile Portlet</short-title>
      <keywords>remove-my-account-webapp</keywords>
    </portlet-info>
  </portlet>

</portlet-app>
